dialog_bot_sdk/__init__.py
dialog_bot_sdk/bot.py
dialog_bot_sdk/entity_manager.py
dialog_bot_sdk/groups.py
dialog_bot_sdk/interactive_media.py
dialog_bot_sdk/messaging.py
dialog_bot_sdk/profile.py
dialog_bot_sdk/service.py
dialog_bot_sdk/updates.py
dialog_bot_sdk/uploading.py
dialog_bot_sdk/users.py
dialog_bot_sdk/utils.py
dialog_bot_sdk/content/__init__.py
dialog_bot_sdk/content/content.py
dialog_bot_sdk/entities/Avatar.py
dialog_bot_sdk/entities/FullUser.py
dialog_bot_sdk/entities/Group.py
dialog_bot_sdk/entities/ListLoadMode.py
dialog_bot_sdk/entities/Peer.py
dialog_bot_sdk/entities/Permissions.py
dialog_bot_sdk/entities/ReferencedEntities.py
dialog_bot_sdk/entities/Sex.py
dialog_bot_sdk/entities/UUID.py
dialog_bot_sdk/entities/UpdateInteractiveMediaEvent.py
dialog_bot_sdk/entities/UpdateMessage.py
dialog_bot_sdk/entities/User.py
dialog_bot_sdk/entities/UserStatus.py
dialog_bot_sdk/entities/__init__.py
dialog_bot_sdk/entities/media/AudioMedia.py
dialog_bot_sdk/entities/media/FileLocation.py
dialog_bot_sdk/entities/media/ImageMedia.py
dialog_bot_sdk/entities/media/InteractiveMediaGroup.py
dialog_bot_sdk/entities/media/WebpageMedia.py
dialog_bot_sdk/entities/media/__init__.py
dialog_bot_sdk/entities/message/DocumentMessage.py
dialog_bot_sdk/entities/message/Message.py
dialog_bot_sdk/entities/message/ServiceMessage.py
dialog_bot_sdk/entities/message/TextMessage.py
dialog_bot_sdk/entities/message/__init__.py
dialog_bot_sdk/exceptions/__init__.py
dialog_bot_sdk/exceptions/exceptions.py
dialog_bot_sdk/internal/__init__.py
dialog_bot_sdk/internal/bot.py
dialog_bot_sdk/internal/service.py
tests/__init__.py
tests/bot.py
tests/run_tests.py
tests/test_bot.py
tests/test_groups.py
tests/test_messaning.py
tests/test_updates.py
tests/test_users.py
dialog_bot_sdk-3.0.8.dist-info/LICENSE
dialog_bot_sdk-3.0.8.dist-info/METADATA
dialog_bot_sdk-3.0.8.dist-info/WHEEL
dialog_bot_sdk-3.0.8.dist-info/top_level.txt
dialog_bot_sdk-3.0.8.dist-info/RECORD
