Metadata-Version: 2.1
Name: dialog-bot-sdk
Version: 3.0.8
Summary: Python Bot SDK for Dialog Messenger
Home-page: https://github.com/dialogs/python-bot-sdk
Author: Dmitry Borodkin, Dialog LLC
Author-email: d.borodkin@dlg.im
License: Apache License 2.0
Keywords: dialog messenger bot sdk
Platform: UNKNOWN
Classifier: Programming Language :: Python :: 3
Classifier: License :: OSI Approved :: Apache Software License
Classifier: Operating System :: OS Independent
Requires-Python: >=3
Requires-Dist: dialog-api (==1.53.0)
Requires-Dist: protobuf (==3.10.0)
Requires-Dist: grpcio (==1.24.1)
Requires-Dist: grpcio-tools (==1.24.1)
Requires-Dist: google-api-python-client (==1.7.11)
Requires-Dist: googleapis-common-protos (==1.6.0)
Requires-Dist: requests (==2.22.0)
Requires-Dist: pyopenssl (==19.0.0)
Requires-Dist: Pillow (==6.2.2)
